setuptools_freeze/__init__.py
setuptools_freeze/constant.py
setuptools_freeze/integration.py
setuptools_freeze-0.0.1.dist-info/LICENSE
setuptools_freeze-0.0.1.dist-info/METADATA
setuptools_freeze-0.0.1.dist-info/WHEEL
setuptools_freeze-0.0.1.dist-info/entry_points.txt
setuptools_freeze-0.0.1.dist-info/top_level.txt
setuptools_freeze-0.0.1.dist-info/RECORD
