Metadata-Version: 2.1
Name: setuptools-freeze
Version: 0.0.1
Summary: Integrate "pyinstaller" to "setuptools"
Home-page: https://github.com/axju/setuptools_freeze
Author: Axel Juraske
Author-email: axel.juraske@short-report.de
License: MIT
Platform: UNKNOWN
Requires-Dist: pyinstaller
